mda/__init__.py
mda/analysis.py
mda/cli.py
mda/elements.py
mda/input.py
mda/log.py
mda/order.py
mda/paper.py
mda/util.py
mda-0.0.3.dist-info/LICENSE
mda-0.0.3.dist-info/METADATA
mda-0.0.3.dist-info/WHEEL
mda-0.0.3.dist-info/entry_points.txt
mda-0.0.3.dist-info/top_level.txt
mda-0.0.3.dist-info/RECORD
