Metadata-Version: 2.1
Name: mda
Version: 0.0.3
Summary: Analysis Tools for MD Simulations
Home-page: https://github.com/ipudu/mda
Author: Pu Du
Author-email: pudugg@gmail.com
License: UNKNOWN
Platform: UNKNOWN
Classifier: Programming Language :: Python :: 3
Classifier: License :: OSI Approved :: MIT License
Classifier: Operating System :: OS Independent
